[
  {
"_comment": "LZP101",
    "persist": {
      "ns": "smm",
      "op": "persistServicePoint",
      "tgtField": "servicePoint",
      "pl": {
        "servicePointCode": "400000000000000000000001",
        "servicePointName": "蓝证平台",
        "status": 0,
        "servicePointAddress": "云端网点",
        "servicePointType": "云端网点",
        "operatingHours": "00:00 - 24:00",
        "contactPerson": "",
        "contactPhone": "",
        "servicePointDescription": "",
        "postalCode": "230904",
        "ct": {
          "uID": "a1ed",
          "oID": "200000000000000000000000"
        },
        "md": {
          "uID": "a1ed",
          "oID": "200000000000000000000000"
        }
      }
    },
    "rename": {
      "ns": "smm",
      "find" : "smm_servicePointCodeInUse",
      "op": "smm_changeServicePointCode",
      "tgtField": "servicePointCode",
      "pl": "LZP101"
    }
  },
  {
"_comment":"LZS101",
    "persist": {
      "ns": "smm",
      "op": "persistService",
      "tgtField": "service",
      "pl": {
        "serviceCode": "LZS101",
        "PriceList": [
          {
            "servicePoint": "LZP101",
            "servicePrices": "0",
            "discountedPrice": "0",
            "paymentMethod": ["1"],
            "remark": "0",
            "pc": "230904",
            "clientCommandAddNew": true,
            "ct": {
              "uID": "a1ed",
              "oID": "200000000000000000000000"
            },
            "md": {
              "uID": "a1ed",
              "oID": "200000000000000000000000"
            }
          }
        ],
        "status": 30,
        "serviceFromSL": "5548375f02f7c81622e557a5",
        "serviceType": "信息核验",
        "standardPayment": ["1"],
        "standardServicePrice": "0",
        "standardPricing": "0",
        "standardServiceNotes": "0",
        "briefOverview": "实名认证服务",
        "serviceName": "实名认证服务",
        "standardReservationRequest": true,
        "ct": {
          "uID": "a1ed",
          "oID": "200000000000000000000000"
        },
        "md": {
          "uID": "a1ed",
          "oID": "200000000000000000000000"
        }
      }
    },
    "rename": {
      "ns": "smm",
      "find":"smm_serviceCodeInUse",
      "op": "smm_changeServiceCode",
      "tgtField": "serviceCode",
      "pl": "LZS101",
      "reid" : "300000000000000000000001"
    }
  },
  {
"_comment": "LZP102",
    "persist": {
      "ns": "smm",
      "op": "persistServicePoint",
      "tgtField": "servicePoint",
      "pl": {
        "servicePointCode": "400000000000000000000002",
        "servicePointName": "蓝证平台",
        "status": 0,
        "servicePointAddress": "云端网点",
        "servicePointType": "云端网点",
        "operatingHours": "00:00 - 24:00",
        "contactPerson": "",
        "contactPhone": "",
        "servicePointDescription": "",
        "postalCode": "230904",
        "ct": {
          "uID": "a1ed",
          "oID": "200000000000000000000000"
        },
        "md": {
          "uID": "a1ed",
          "oID": "200000000000000000000000"
        }
      }
    },
    "rename": {
      "ns": "smm",
      "find" : "smm_servicePointCodeInUse",
      "op": "smm_changeServicePointCode",
      "tgtField": "servicePointCode",
      "pl": "LZP102"
    }
  },
  {
"_comment":"LZS102",
    "persist": {
      "ns": "smm",
      "op": "persistService",
      "tgtField": "service",
      "pl": {
        "serviceCode": "LZS102",
        "PriceList": [
          {
            "servicePoint": "LZP102",
            "servicePrices": "0",
            "discountedPrice": "0",
            "paymentMethod": ["1"],
            "remark": "0",
            "pc": "230904",
            "clientCommandAddNew": true,
            "ct": {
              "uID": "a1ed",
              "oID": "200000000000000000000000"
            },
            "md": {
              "uID": "a1ed",
              "oID": "200000000000000000000000"
            }
          }
        ],
        "status": 30,
        "serviceFromSL": "5548375f02f7c81622e557a5",
        "serviceType": "信息核验",
        "standardPayment": ["1"],
        "standardServicePrice": "0",
        "standardPricing": "0",
        "standardServiceNotes": "0",
        "briefOverview": "蓝证证照核验",
        "serviceName": "蓝证证照核验服务",
        "standardReservationRequest": true,
        "ct": {
          "uID": "a1ed",
          "oID": "200000000000000000000000"
        },
        "md": {
          "uID": "a1ed",
          "oID": "200000000000000000000000"
        }
      }
    },
    "rename": {
      "ns": "smm",
      "find":"smm_serviceCodeInUse",
      "op": "smm_changeServiceCode",
      "tgtField": "serviceCode",
      "pl": "LZS102",
      "reid" : "300000000000000000000002"
    }
  }
]